[
  {
    "Id": 2,
    "Name": "1984",
    "Author": "George Orwell",
    "IsAvailable": false,
    "YearOfPublish": 1949,
    "LiteraryGenre": "Dystopian",
    "Price": 1.0
  },
  {
    "Id": 3,
    "Name": "ytosdiystodi",
    "Author": "srtyisiry",
    "IsAvailable": false,
    "YearOfPublish": 2004,
    "LiteraryGenre": "SF",
    "Price": 15.0
  },
  {
    "Id": 4,
    "Name": "tuazufhkz",
    "Author": "dturza",
    "IsAvailable": true,
    "YearOfPublish": 2000,
    "LiteraryGenre": "SF",
    "Price": 16.0
  },
  {
    "Id": 6,
    "Name": "1984",
    "Author": "George Orwell",
    "IsAvailable": false,
    "YearOfPublish": 1990,
    "LiteraryGenre": "Dystopian",
    "Price": 11.0
  },
  {
    "Id": 7,
    "Name": "tfjtfstsf",
    "Author": "fgstgfftgu",
    "IsAvailable": true,
    "YearOfPublish": 2000,
    "LiteraryGenre": "ghfj",
    "Price": 123.0
  }
]